README.rst
setup.py
hellomeme/__init__.py
hellomeme/welcome.py
hellomeme.egg-info/PKG-INFO
hellomeme.egg-info/SOURCES.txt
hellomeme.egg-info/dependency_links.txt
hellomeme.egg-info/not-zip-safe
hellomeme.egg-info/top_level.txt